README.rst
setup.cfg
setup.py
bumbling.egg-info/PKG-INFO
bumbling.egg-info/SOURCES.txt
bumbling.egg-info/dependency_links.txt
bumbling.egg-info/entry_points.txt
bumbling.egg-info/requires.txt
bumbling.egg-info/top_level.txt
src/__init__.py
src/bumbling.py