Metadata-Version: 2.1
Name: bumbling
Version: 1.1
Summary: UNKNOWN
Home-page: https://github.com/JonathanRoth13/bumbling
Author: Jonathan Roth
Author-email: JonathanRoth@protonmail.com
License: MIT
Platform: UNKNOWN
